{
  "blueprint": {
    "entities": [
      {
        "direction": 2,
        "entity_number": 1,
        "name": "fast-transport-belt",
        "position": {
          "x": 177.5,
          "y": 8.5
        }
      },
      {
        "direction": 2,
        "entity_number": 2,
        "name": "fast-transport-belt",
        "position": {
          "x": 179.5,
          "y": 8.5
        }
      },
      {
        "direction": 2,
        "entity_number": 3,
        "name": "fast-transport-belt",
        "position": {
          "x": 178.5,
          "y": 8.5
        }
      },
      {
        "direction": 2,
        "entity_number": 4,
        "name": "fast-transport-belt",
        "position": {
          "x": 181.5,
          "y": 8.5
        }
      },
      {
        "direction": 2,
        "entity_number": 5,
        "name": "fast-transport-belt",
        "position": {
          "x": 180.5,
          "y": 8.5
        }
      },
      {
        "direction": 4,
        "entity_number": 6,
        "name": "fast-transport-belt",
        "position": {
          "x": 183.5,
          "y": 8.5
        }
      },
      {
        "direction": 4,
        "entity_number": 7,
        "name": "fast-transport-belt",
        "position": {
          "x": 183.5,
          "y": 9.5
        }
      },
      {
        "direction": 2,
        "entity_number": 8,
        "name": "fast-transport-belt",
        "position": {
          "x": 182.5,
          "y": 8.5
        }
      },
      {
        "direction": 4,
        "entity_number": 9,
        "name": "fast-transport-belt",
        "position": {
          "x": 183.5,
          "y": 10.5
        }
      },
      {
        "direction": 4,
        "entity_number": 10,
        "name": "fast-transport-belt",
        "position": {
          "x": 183.5,
          "y": 11.5
        }
      },
      {
        "direction": 4,
        "entity_number": 11,
        "name": "fast-transport-belt",
        "position": {
          "x": 183.5,
          "y": 12.5
        }
      },
      {
        "direction": 4,
        "entity_number": 12,
        "name": "fast-transport-belt",
        "position": {
          "x": 183.5,
          "y": 13.5
        }
      },
      {
        "direction": 2,
        "entity_number": 13,
        "name": "fast-transport-belt",
        "position": {
          "x": 180.5,
          "y": 14.5
        }
      },
      {
        "direction": 2,
        "entity_number": 14,
        "name": "fast-transport-belt",
        "position": {
          "x": 181.5,
          "y": 14.5
        }
      },
      {
        "entity_number": 15,
        "name": "fast-transport-belt",
        "position": {
          "x": 180.5,
          "y": 15.5
        }
      },
      {
        "direction": 2,
        "entity_number": 16,
        "name": "fast-underground-belt",
        "position": {
          "x": 182.5,
          "y": 14.5
        },
        "type": "input"
      },
      {
        "direction": 4,
        "entity_number": 17,
        "name": "fast-transport-belt",
        "position": {
          "x": 183.5,
          "y": 14.5
        }
      },
      {
        "direction": 4,
        "entity_number": 18,
        "name": "fast-transport-belt",
        "position": {
          "x": 183.5,
          "y": 15.5
        }
      },
      {
        "direction": 2,
        "entity_number": 19,
        "name": "fast-underground-belt",
        "position": {
          "x": 184.5,
          "y": 14.5
        },
        "type": "output"
      },
      {
        "direction": 2,
        "entity_number": 20,
        "name": "fast-transport-belt",
        "position": {
          "x": 185.5,
          "y": 14.5
        }
      },
      {
        "direction": 2,
        "entity_number": 21,
        "name": "fast-transport-belt",
        "position": {
          "x": 186.5,
          "y": 14.5
        }
      },
      {
        "direction": 2,
        "entity_number": 22,
        "name": "fast-transport-belt",
        "position": {
          "x": 187.5,
          "y": 14.5
        }
      },
      {
        "direction": 2,
        "entity_number": 23,
        "name": "fast-transport-belt",
        "position": {
          "x": 188.5,
          "y": 14.5
        }
      },
      {
        "direction": 2,
        "entity_number": 24,
        "name": "fast-transport-belt",
        "position": {
          "x": 189.5,
          "y": 14.5
        }
      },
      {
        "direction": 2,
        "entity_number": 25,
        "name": "fast-transport-belt",
        "position": {
          "x": 191.5,
          "y": 14.5
        }
      },
      {
        "direction": 2,
        "entity_number": 26,
        "name": "fast-transport-belt",
        "position": {
          "x": 190.5,
          "y": 14.5
        }
      },
      {
        "entity_number": 27,
        "name": "fast-inserter",
        "position": {
          "x": 190.5,
          "y": 15.5
        }
      },
      {
        "entity_number": 28,
        "name": "medium-electric-pole",
        "neighbours": [
          32,
          66
        ],
        "position": {
          "x": 192.5,
          "y": 15.5
        }
      },
      {
        "direction": 2,
        "entity_number": 29,
        "name": "fast-transport-belt",
        "position": {
          "x": 193.5,
          "y": 14.5
        }
      },
      {
        "direction": 2,
        "entity_number": 30,
        "name": "fast-transport-belt",
        "position": {
          "x": 192.5,
          "y": 14.5
        }
      },
      {
        "entity_number": 31,
        "name": "fast-inserter",
        "position": {
          "x": 193.5,
          "y": 15.5
        }
      },
      {
        "entity_number": 32,
        "name": "medium-electric-pole",
        "neighbours": [
          28,
          41
        ],
        "position": {
          "x": 195.5,
          "y": 15.5
        }
      },
      {
        "direction": 2,
        "entity_number": 33,
        "name": "fast-transport-belt",
        "position": {
          "x": 195.5,
          "y": 14.5
        }
      },
      {
        "direction": 2,
        "entity_number": 34,
        "name": "fast-transport-belt",
        "position": {
          "x": 194.5,
          "y": 14.5
        }
      },
      {
        "direction": 2,
        "entity_number": 35,
        "name": "fast-transport-belt",
        "position": {
          "x": 197.5,
          "y": 14.5
        }
      },
      {
        "direction": 2,
        "entity_number": 36,
        "name": "fast-transport-belt",
        "position": {
          "x": 196.5,
          "y": 14.5
        }
      },
      {
        "entity_number": 37,
        "name": "fast-inserter",
        "position": {
          "x": 196.5,
          "y": 15.5
        }
      },
      {
        "entity_number": 38,
        "name": "fast-inserter",
        "position": {
          "x": 199.5,
          "y": 15.5
        }
      },
      {
        "direction": 2,
        "entity_number": 39,
        "name": "fast-transport-belt",
        "position": {
          "x": 199.5,
          "y": 14.5
        }
      },
      {
        "direction": 2,
        "entity_number": 40,
        "name": "fast-transport-belt",
        "position": {
          "x": 198.5,
          "y": 14.5
        }
      },
      {
        "entity_number": 41,
        "name": "medium-electric-pole",
        "neighbours": [
          32,
          47,
          72
        ],
        "position": {
          "x": 201.5,
          "y": 15.5
        }
      },
      {
        "direction": 2,
        "entity_number": 42,
        "name": "fast-transport-belt",
        "position": {
          "x": 201.5,
          "y": 14.5
        }
      },
      {
        "direction": 2,
        "entity_number": 43,
        "name": "fast-transport-belt",
        "position": {
          "x": 200.5,
          "y": 14.5
        }
      },
      {
        "entity_number": 44,
        "name": "fast-inserter",
        "position": {
          "x": 202.5,
          "y": 15.5
        }
      },
      {
        "direction": 2,
        "entity_number": 45,
        "name": "fast-transport-belt",
        "position": {
          "x": 203.5,
          "y": 14.5
        }
      },
      {
        "direction": 2,
        "entity_number": 46,
        "name": "fast-transport-belt",
        "position": {
          "x": 202.5,
          "y": 14.5
        }
      },
      {
        "entity_number": 47,
        "name": "medium-electric-pole",
        "neighbours": [
          41
        ],
        "position": {
          "x": 204.5,
          "y": 15.5
        }
      },
      {
        "entity_number": 48,
        "name": "fast-inserter",
        "position": {
          "x": 205.5,
          "y": 15.5
        }
      },
      {
        "direction": 2,
        "entity_number": 49,
        "name": "fast-transport-belt",
        "position": {
          "x": 205.5,
          "y": 14.5
        }
      },
      {
        "direction": 2,
        "entity_number": 50,
        "name": "fast-transport-belt",
        "position": {
          "x": 204.5,
          "y": 14.5
        }
      },
      {
        "entity_number": 51,
        "name": "fast-transport-belt",
        "position": {
          "x": 180.5,
          "y": 16.5
        }
      },
      {
        "entity_number": 52,
        "name": "fast-transport-belt",
        "position": {
          "x": 180.5,
          "y": 17.5
        }
      },
      {
        "direction": 4,
        "entity_number": 53,
        "name": "fast-transport-belt",
        "position": {
          "x": 183.5,
          "y": 16.5
        }
      },
      {
        "direction": 4,
        "entity_number": 54,
        "name": "fast-transport-belt",
        "position": {
          "x": 183.5,
          "y": 17.5
        }
      },
      {
        "entity_number": 55,
        "name": "assembling-machine-2",
        "position": {
          "x": 190.5,
          "y": 17.5
        },
        "recipe": "copper-cable"
      },
      {
        "entity_number": 56,
        "name": "assembling-machine-2",
        "position": {
          "x": 193.5,
          "y": 17.5
        },
        "recipe": "copper-cable"
      },
      {
        "entity_number": 57,
        "name": "assembling-machine-2",
        "position": {
          "x": 196.5,
          "y": 17.5
        },
        "recipe": "copper-cable"
      },
      {
        "entity_number": 58,
        "name": "assembling-machine-2",
        "position": {
          "x": 199.5,
          "y": 17.5
        },
        "recipe": "copper-cable"
      },
      {
        "entity_number": 59,
        "name": "assembling-machine-2",
        "position": {
          "x": 202.5,
          "y": 17.5
        },
        "recipe": "copper-cable"
      },
      {
        "entity_number": 60,
        "name": "assembling-machine-2",
        "position": {
          "x": 205.5,
          "y": 17.5
        },
        "recipe": "copper-cable"
      },
      {
        "entity_number": 61,
        "name": "fast-transport-belt",
        "position": {
          "x": 180.5,
          "y": 18.5
        }
      },
      {
        "entity_number": 62,
        "name": "fast-transport-belt",
        "position": {
          "x": 180.5,
          "y": 19.5
        }
      },
      {
        "direction": 4,
        "entity_number": 63,
        "name": "fast-transport-belt",
        "position": {
          "x": 183.5,
          "y": 18.5
        }
      },
      {
        "direction": 4,
        "entity_number": 64,
        "name": "fast-transport-belt",
        "position": {
          "x": 183.5,
          "y": 19.5
        }
      },
      {
        "entity_number": 65,
        "name": "fast-inserter",
        "position": {
          "x": 191.5,
          "y": 19.5
        }
      },
      {
        "entity_number": 66,
        "name": "medium-electric-pole",
        "neighbours": [
          28,
          95,
          102,
          152
        ],
        "position": {
          "x": 193.5,
          "y": 19.5
        }
      },
      {
        "entity_number": 67,
        "name": "fast-inserter",
        "position": {
          "x": 192.5,
          "y": 19.5
        }
      },
      {
        "entity_number": 68,
        "name": "fast-inserter",
        "position": {
          "x": 195.5,
          "y": 19.5
        }
      },
      {
        "entity_number": 69,
        "name": "fast-inserter",
        "position": {
          "x": 194.5,
          "y": 19.5
        }
      },
      {
        "entity_number": 70,
        "name": "fast-inserter",
        "position": {
          "x": 201.5,
          "y": 19.5
        }
      },
      {
        "entity_number": 71,
        "name": "fast-inserter",
        "position": {
          "x": 200.5,
          "y": 19.5
        }
      },
      {
        "entity_number": 72,
        "name": "medium-electric-pole",
        "neighbours": [
          41,
          109,
          162
        ],
        "position": {
          "x": 202.5,
          "y": 19.5
        }
      },
      {
        "entity_number": 73,
        "name": "fast-inserter",
        "position": {
          "x": 203.5,
          "y": 19.5
        }
      },
      {
        "entity_number": 74,
        "name": "fast-inserter",
        "position": {
          "x": 204.5,
          "y": 19.5
        }
      },
      {
        "entity_number": 75,
        "name": "fast-transport-belt",
        "position": {
          "x": 180.5,
          "y": 20.5
        }
      },
      {
        "entity_number": 76,
        "name": "fast-transport-belt",
        "position": {
          "x": 180.5,
          "y": 21.5
        }
      },
      {
        "direction": 4,
        "entity_number": 77,
        "name": "fast-transport-belt",
        "position": {
          "x": 183.5,
          "y": 20.5
        }
      },
      {
        "direction": 4,
        "entity_number": 78,
        "name": "fast-transport-belt",
        "position": {
          "x": 183.5,
          "y": 21.5
        }
      },
      {
        "direction": 6,
        "entity_number": 79,
        "name": "fast-inserter",
        "position": {
          "x": 184.5,
          "y": 21.5
        }
      },
      {
        "entity_number": 80,
        "name": "assembling-machine-2",
        "position": {
          "x": 186.5,
          "y": 21.5
        },
        "recipe": "stone-tablet"
      },
      {
        "direction": 6,
        "entity_number": 81,
        "name": "fast-inserter",
        "position": {
          "x": 188.5,
          "y": 20.5
        }
      },
      {
        "direction": 4,
        "entity_number": 82,
        "name": "fast-transport-belt",
        "position": {
          "x": 189.5,
          "y": 20.5
        }
      },
      {
        "direction": 4,
        "entity_number": 83,
        "name": "fast-transport-belt",
        "position": {
          "x": 189.5,
          "y": 21.5
        }
      },
      {
        "direction": 6,
        "entity_number": 84,
        "name": "fast-inserter",
        "position": {
          "x": 188.5,
          "y": 21.5
        }
      },
      {
        "entity_number": 85,
        "name": "assembling-machine-2",
        "position": {
          "x": 191.5,
          "y": 21.5
        },
        "recipe": "electronic-circuit-stone"
      },
      {
        "entity_number": 86,
        "name": "assembling-machine-2",
        "position": {
          "x": 195.5,
          "y": 21.5
        },
        "recipe": "electronic-circuit-stone"
      },
      {
        "entity_number": 87,
        "name": "assembling-machine-2",
        "position": {
          "x": 200.5,
          "y": 21.5
        },
        "recipe": "electronic-circuit-stone"
      },
      {
        "entity_number": 88,
        "name": "assembling-machine-2",
        "position": {
          "x": 204.5,
          "y": 21.5
        },
        "recipe": "electronic-circuit-stone"
      },
      {
        "entity_number": 89,
        "name": "fast-transport-belt",
        "position": {
          "x": 180.5,
          "y": 22.5
        }
      },
      {
        "entity_number": 90,
        "name": "fast-transport-belt",
        "position": {
          "x": 180.5,
          "y": 23.5
        }
      },
      {
        "direction": 4,
        "entity_number": 91,
        "name": "fast-transport-belt",
        "position": {
          "x": 183.5,
          "y": 22.5
        }
      },
      {
        "direction": 4,
        "entity_number": 92,
        "name": "fast-transport-belt",
        "position": {
          "x": 183.5,
          "y": 23.5
        }
      },
      {
        "entity_number": 93,
        "name": "medium-electric-pole",
        "neighbours": [
          95,
          115
        ],
        "position": {
          "x": 184.5,
          "y": 22.5
        }
      },
      {
        "entity_number": 94,
        "name": "assembling-machine-2",
        "position": {
          "x": 186.5,
          "y": 24.5
        },
        "recipe": "stone-tablet"
      },
      {
        "entity_number": 95,
        "name": "medium-electric-pole",
        "neighbours": [
          93,
          66,
          99,
          116
        ],
        "position": {
          "x": 188.5,
          "y": 22.5
        }
      },
      {
        "direction": 4,
        "entity_number": 96,
        "name": "fast-transport-belt",
        "position": {
          "x": 189.5,
          "y": 22.5
        }
      },
      {
        "direction": 4,
        "entity_number": 97,
        "name": "fast-transport-belt",
        "position": {
          "x": 189.5,
          "y": 23.5
        }
      },
      {
        "direction": 6,
        "entity_number": 98,
        "name": "fast-inserter",
        "position": {
          "x": 188.5,
          "y": 23.5
        }
      },
      {
        "entity_number": 99,
        "name": "medium-electric-pole",
        "neighbours": [
          95,
          102,
          115,
          152
        ],
        "position": {
          "x": 191.5,
          "y": 23.5
        }
      },
      {
        "direction": 4,
        "entity_number": 100,
        "name": "inserter",
        "position": {
          "x": 190.5,
          "y": 23.5
        }
      },
      {
        "entity_number": 101,
        "name": "long-handed-inserter",
        "position": {
          "x": 192.5,
          "y": 23.5
        }
      },
      {
        "entity_number": 102,
        "name": "medium-electric-pole",
        "neighbours": [
          99,
          66,
          106,
          156,
          174
        ],
        "position": {
          "x": 195.5,
          "y": 23.5
        }
      },
      {
        "direction": 4,
        "entity_number": 103,
        "name": "inserter",
        "position": {
          "x": 194.5,
          "y": 23.5
        }
      },
      {
        "entity_number": 104,
        "name": "long-handed-inserter",
        "position": {
          "x": 196.5,
          "y": 23.5
        }
      },
      {
        "direction": 4,
        "entity_number": 105,
        "name": "inserter",
        "position": {
          "x": 199.5,
          "y": 23.5
        }
      },
      {
        "entity_number": 106,
        "name": "medium-electric-pole",
        "neighbours": [
          102,
          109,
          162
        ],
        "position": {
          "x": 200.5,
          "y": 23.5
        }
      },
      {
        "entity_number": 107,
        "name": "long-handed-inserter",
        "position": {
          "x": 201.5,
          "y": 23.5
        }
      },
      {
        "direction": 4,
        "entity_number": 108,
        "name": "inserter",
        "position": {
          "x": 203.5,
          "y": 23.5
        }
      },
      {
        "entity_number": 109,
        "name": "medium-electric-pole",
        "neighbours": [
          106,
          72,
          166,
          184
        ],
        "position": {
          "x": 204.5,
          "y": 23.5
        }
      },
      {
        "entity_number": 110,
        "name": "long-handed-inserter",
        "position": {
          "x": 205.5,
          "y": 23.5
        }
      },
      {
        "entity_number": 111,
        "name": "fast-transport-belt",
        "position": {
          "x": 180.5,
          "y": 24.5
        }
      },
      {
        "entity_number": 112,
        "name": "fast-transport-belt",
        "position": {
          "x": 180.5,
          "y": 25.5
        }
      },
      {
        "direction": 4,
        "entity_number": 113,
        "name": "fast-transport-belt",
        "position": {
          "x": 183.5,
          "y": 24.5
        }
      },
      {
        "direction": 6,
        "entity_number": 114,
        "name": "fast-inserter",
        "position": {
          "x": 184.5,
          "y": 24.5
        }
      },
      {
        "entity_number": 115,
        "name": "medium-electric-pole",
        "neighbours": [
          99,
          93,
          116
        ],
        "position": {
          "x": 184.5,
          "y": 25.5
        }
      },
      {
        "entity_number": 116,
        "name": "medium-electric-pole",
        "neighbours": [
          115,
          95,
          152
        ],
        "position": {
          "x": 188.5,
          "y": 25.5
        }
      },
      {
        "direction": 2,
        "entity_number": 117,
        "name": "fast-transport-belt",
        "position": {
          "x": 189.5,
          "y": 24.5
        }
      },
      {
        "direction": 6,
        "entity_number": 118,
        "name": "fast-inserter",
        "position": {
          "x": 188.5,
          "y": 24.5
        }
      },
      {
        "direction": 2,
        "entity_number": 119,
        "name": "fast-transport-belt",
        "position": {
          "x": 191.5,
          "y": 25.5
        }
      },
      {
        "direction": 2,
        "entity_number": 120,
        "name": "fast-transport-belt",
        "position": {
          "x": 190.5,
          "y": 25.5
        }
      },
      {
        "direction": 2,
        "entity_number": 121,
        "name": "fast-transport-belt",
        "position": {
          "x": 191.5,
          "y": 24.5
        }
      },
      {
        "direction": 2,
        "entity_number": 122,
        "name": "fast-transport-belt",
        "position": {
          "x": 190.5,
          "y": 24.5
        }
      },
      {
        "direction": 2,
        "entity_number": 123,
        "name": "fast-transport-belt",
        "position": {
          "x": 193.5,
          "y": 25.5
        }
      },
      {
        "direction": 2,
        "entity_number": 124,
        "name": "fast-transport-belt",
        "position": {
          "x": 192.5,
          "y": 25.5
        }
      },
      {
        "direction": 2,
        "entity_number": 125,
        "name": "fast-transport-belt",
        "position": {
          "x": 193.5,
          "y": 24.5
        }
      },
      {
        "direction": 2,
        "entity_number": 126,
        "name": "fast-transport-belt",
        "position": {
          "x": 192.5,
          "y": 24.5
        }
      },
      {
        "direction": 2,
        "entity_number": 127,
        "name": "fast-transport-belt",
        "position": {
          "x": 195.5,
          "y": 25.5
        }
      },
      {
        "direction": 2,
        "entity_number": 128,
        "name": "fast-transport-belt",
        "position": {
          "x": 194.5,
          "y": 25.5
        }
      },
      {
        "direction": 2,
        "entity_number": 129,
        "name": "fast-transport-belt",
        "position": {
          "x": 195.5,
          "y": 24.5
        }
      },
      {
        "direction": 2,
        "entity_number": 130,
        "name": "fast-transport-belt",
        "position": {
          "x": 194.5,
          "y": 24.5
        }
      },
      {
        "direction": 2,
        "entity_number": 131,
        "name": "fast-transport-belt",
        "position": {
          "x": 197.5,
          "y": 25.5
        }
      },
      {
        "direction": 2,
        "entity_number": 132,
        "name": "fast-transport-belt",
        "position": {
          "x": 196.5,
          "y": 25.5
        }
      },
      {
        "direction": 2,
        "entity_number": 133,
        "name": "fast-transport-belt",
        "position": {
          "x": 197.5,
          "y": 24.5
        }
      },
      {
        "direction": 2,
        "entity_number": 134,
        "name": "fast-transport-belt",
        "position": {
          "x": 196.5,
          "y": 24.5
        }
      },
      {
        "direction": 2,
        "entity_number": 135,
        "name": "fast-transport-belt",
        "position": {
          "x": 199.5,
          "y": 25.5
        }
      },
      {
        "direction": 2,
        "entity_number": 136,
        "name": "fast-transport-belt",
        "position": {
          "x": 198.5,
          "y": 25.5
        }
      },
      {
        "direction": 2,
        "entity_number": 137,
        "name": "fast-transport-belt",
        "position": {
          "x": 199.5,
          "y": 24.5
        }
      },
      {
        "direction": 2,
        "entity_number": 138,
        "name": "fast-transport-belt",
        "position": {
          "x": 198.5,
          "y": 24.5
        }
      },
      {
        "direction": 2,
        "entity_number": 139,
        "name": "fast-transport-belt",
        "position": {
          "x": 201.5,
          "y": 25.5
        }
      },
      {
        "direction": 2,
        "entity_number": 140,
        "name": "fast-transport-belt",
        "position": {
          "x": 200.5,
          "y": 25.5
        }
      },
      {
        "direction": 2,
        "entity_number": 141,
        "name": "fast-transport-belt",
        "position": {
          "x": 201.5,
          "y": 24.5
        }
      },
      {
        "direction": 2,
        "entity_number": 142,
        "name": "fast-transport-belt",
        "position": {
          "x": 200.5,
          "y": 24.5
        }
      },
      {
        "direction": 2,
        "entity_number": 143,
        "name": "fast-transport-belt",
        "position": {
          "x": 203.5,
          "y": 25.5
        }
      },
      {
        "direction": 2,
        "entity_number": 144,
        "name": "fast-transport-belt",
        "position": {
          "x": 202.5,
          "y": 25.5
        }
      },
      {
        "direction": 2,
        "entity_number": 145,
        "name": "fast-transport-belt",
        "position": {
          "x": 203.5,
          "y": 24.5
        }
      },
      {
        "direction": 2,
        "entity_number": 146,
        "name": "fast-transport-belt",
        "position": {
          "x": 202.5,
          "y": 24.5
        }
      },
      {
        "direction": 2,
        "entity_number": 147,
        "name": "fast-transport-belt",
        "position": {
          "x": 205.5,
          "y": 25.5
        }
      },
      {
        "direction": 2,
        "entity_number": 148,
        "name": "fast-transport-belt",
        "position": {
          "x": 204.5,
          "y": 25.5
        }
      },
      {
        "direction": 2,
        "entity_number": 149,
        "name": "fast-transport-belt",
        "position": {
          "x": 206.5,
          "y": 25.5
        }
      },
      {
        "entity_number": 150,
        "name": "fast-transport-belt",
        "position": {
          "x": 180.5,
          "y": 26.5
        }
      },
      {
        "entity_number": 151,
        "name": "fast-transport-belt",
        "position": {
          "x": 180.5,
          "y": 27.5
        }
      },
      {
        "entity_number": 152,
        "name": "medium-electric-pole",
        "neighbours": [
          116,
          99,
          66,
          156,
          174
        ],
        "position": {
          "x": 191.5,
          "y": 26.5
        }
      },
      {
        "entity_number": 153,
        "name": "long-handed-inserter",
        "position": {
          "x": 190.5,
          "y": 26.5
        }
      },
      {
        "direction": 4,
        "entity_number": 154,
        "name": "assembling-machine-2",
        "position": {
          "x": 191.5,
          "y": 28.5
        },
        "recipe": "electronic-circuit-stone"
      },
      {
        "direction": 4,
        "entity_number": 155,
        "name": "inserter",
        "position": {
          "x": 192.5,
          "y": 26.5
        }
      },
      {
        "entity_number": 156,
        "name": "medium-electric-pole",
        "neighbours": [
          152,
          102,
          162
        ],
        "position": {
          "x": 195.5,
          "y": 26.5
        }
      },
      {
        "entity_number": 157,
        "name": "long-handed-inserter",
        "position": {
          "x": 194.5,
          "y": 26.5
        }
      },
      {
        "direction": 4,
        "entity_number": 158,
        "name": "assembling-machine-2",
        "position": {
          "x": 195.5,
          "y": 28.5
        },
        "recipe": "electronic-circuit-stone"
      },
      {
        "direction": 4,
        "entity_number": 159,
        "name": "inserter",
        "position": {
          "x": 196.5,
          "y": 26.5
        }
      },
      {
        "entity_number": 160,
        "name": "long-handed-inserter",
        "position": {
          "x": 199.5,
          "y": 26.5
        }
      },
      {
        "direction": 4,
        "entity_number": 161,
        "name": "assembling-machine-2",
        "position": {
          "x": 200.5,
          "y": 28.5
        },
        "recipe": "electronic-circuit-stone"
      },
      {
        "entity_number": 162,
        "name": "medium-electric-pole",
        "neighbours": [
          156,
          106,
          72,
          166,
          184
        ],
        "position": {
          "x": 200.5,
          "y": 26.5
        }
      },
      {
        "direction": 4,
        "entity_number": 163,
        "name": "inserter",
        "position": {
          "x": 201.5,
          "y": 26.5
        }
      },
      {
        "entity_number": 164,
        "name": "long-handed-inserter",
        "position": {
          "x": 203.5,
          "y": 26.5
        }
      },
      {
        "direction": 4,
        "entity_number": 165,
        "name": "assembling-machine-2",
        "position": {
          "x": 204.5,
          "y": 28.5
        },
        "recipe": "electronic-circuit-stone"
      },
      {
        "entity_number": 166,
        "name": "medium-electric-pole",
        "neighbours": [
          162,
          109
        ],
        "position": {
          "x": 204.5,
          "y": 26.5
        }
      },
      {
        "direction": 4,
        "entity_number": 167,
        "name": "inserter",
        "position": {
          "x": 205.5,
          "y": 26.5
        }
      },
      {
        "entity_number": 168,
        "name": "fast-transport-belt",
        "position": {
          "x": 180.5,
          "y": 28.5
        }
      },
      {
        "entity_number": 169,
        "name": "fast-transport-belt",
        "position": {
          "x": 180.5,
          "y": 29.5
        }
      },
      {
        "entity_number": 170,
        "name": "fast-transport-belt",
        "position": {
          "x": 180.5,
          "y": 30.5
        }
      },
      {
        "entity_number": 171,
        "name": "fast-transport-belt",
        "position": {
          "x": 180.5,
          "y": 31.5
        }
      },
      {
        "direction": 4,
        "entity_number": 172,
        "name": "assembling-machine-2",
        "position": {
          "x": 190.5,
          "y": 32.5
        },
        "recipe": "copper-cable"
      },
      {
        "direction": 4,
        "entity_number": 173,
        "name": "fast-inserter",
        "position": {
          "x": 191.5,
          "y": 30.5
        }
      },
      {
        "entity_number": 174,
        "name": "medium-electric-pole",
        "neighbours": [
          152,
          102,
          208
        ],
        "position": {
          "x": 193.5,
          "y": 30.5
        }
      },
      {
        "direction": 4,
        "entity_number": 175,
        "name": "fast-inserter",
        "position": {
          "x": 192.5,
          "y": 30.5
        }
      },
      {
        "direction": 4,
        "entity_number": 176,
        "name": "assembling-machine-2",
        "position": {
          "x": 193.5,
          "y": 32.5
        },
        "recipe": "copper-cable"
      },
      {
        "direction": 4,
        "entity_number": 177,
        "name": "fast-inserter",
        "position": {
          "x": 194.5,
          "y": 30.5
        }
      },
      {
        "direction": 4,
        "entity_number": 178,
        "name": "fast-inserter",
        "position": {
          "x": 195.5,
          "y": 30.5
        }
      },
      {
        "direction": 4,
        "entity_number": 179,
        "name": "assembling-machine-2",
        "position": {
          "x": 196.5,
          "y": 32.5
        },
        "recipe": "copper-cable"
      },
      {
        "direction": 4,
        "entity_number": 180,
        "name": "assembling-machine-2",
        "position": {
          "x": 199.5,
          "y": 32.5
        },
        "recipe": "copper-cable"
      },
      {
        "direction": 4,
        "entity_number": 181,
        "name": "fast-inserter",
        "position": {
          "x": 200.5,
          "y": 30.5
        }
      },
      {
        "direction": 4,
        "entity_number": 182,
        "name": "fast-inserter",
        "position": {
          "x": 201.5,
          "y": 30.5
        }
      },
      {
        "direction": 4,
        "entity_number": 183,
        "name": "assembling-machine-2",
        "position": {
          "x": 202.5,
          "y": 32.5
        },
        "recipe": "copper-cable"
      },
      {
        "entity_number": 184,
        "name": "medium-electric-pole",
        "neighbours": [
          162,
          109,
          220
        ],
        "position": {
          "x": 202.5,
          "y": 30.5
        }
      },
      {
        "direction": 4,
        "entity_number": 185,
        "name": "fast-inserter",
        "position": {
          "x": 203.5,
          "y": 30.5
        }
      },
      {
        "direction": 4,
        "entity_number": 186,
        "name": "fast-inserter",
        "position": {
          "x": 204.5,
          "y": 30.5
        }
      },
      {
        "direction": 4,
        "entity_number": 187,
        "name": "assembling-machine-2",
        "position": {
          "x": 205.5,
          "y": 32.5
        },
        "recipe": "copper-cable"
      },
      {
        "entity_number": 188,
        "name": "fast-transport-belt",
        "position": {
          "x": 180.5,
          "y": 32.5
        }
      },
      {
        "entity_number": 189,
        "name": "fast-transport-belt",
        "position": {
          "x": 180.5,
          "y": 33.5
        }
      },
      {
        "direction": 2,
        "entity_number": 190,
        "name": "fast-transport-belt",
        "position": {
          "x": 181.5,
          "y": 35.5
        }
      },
      {
        "entity_number": 191,
        "name": "fast-transport-belt",
        "position": {
          "x": 180.5,
          "y": 34.5
        }
      },
      {
        "entity_number": 192,
        "name": "fast-transport-belt",
        "position": {
          "x": 180.5,
          "y": 35.5
        }
      },
      {
        "direction": 2,
        "entity_number": 193,
        "name": "fast-transport-belt",
        "position": {
          "x": 182.5,
          "y": 35.5
        }
      },
      {
        "direction": 2,
        "entity_number": 194,
        "name": "fast-transport-belt",
        "position": {
          "x": 183.5,
          "y": 35.5
        }
      },
      {
        "direction": 2,
        "entity_number": 195,
        "name": "fast-transport-belt",
        "position": {
          "x": 184.5,
          "y": 35.5
        }
      },
      {
        "direction": 2,
        "entity_number": 196,
        "name": "fast-transport-belt",
        "position": {
          "x": 185.5,
          "y": 35.5
        }
      },
      {
        "direction": 2,
        "entity_number": 197,
        "name": "fast-transport-belt",
        "position": {
          "x": 186.5,
          "y": 35.5
        }
      },
      {
        "direction": 2,
        "entity_number": 198,
        "name": "fast-transport-belt",
        "position": {
          "x": 187.5,
          "y": 35.5
        }
      },
      {
        "direction": 2,
        "entity_number": 199,
        "name": "fast-transport-belt",
        "position": {
          "x": 188.5,
          "y": 35.5
        }
      },
      {
        "direction": 2,
        "entity_number": 200,
        "name": "fast-transport-belt",
        "position": {
          "x": 189.5,
          "y": 35.5
        }
      },
      {
        "entity_number": 201,
        "name": "medium-electric-pole",
        "neighbours": [
          208
        ],
        "position": {
          "x": 191.5,
          "y": 34.5
        }
      },
      {
        "direction": 2,
        "entity_number": 202,
        "name": "fast-transport-belt",
        "position": {
          "x": 191.5,
          "y": 35.5
        }
      },
      {
        "direction": 2,
        "entity_number": 203,
        "name": "fast-transport-belt",
        "position": {
          "x": 190.5,
          "y": 35.5
        }
      },
      {
        "direction": 4,
        "entity_number": 204,
        "name": "fast-inserter",
        "position": {
          "x": 190.5,
          "y": 34.5
        }
      },
      {
        "direction": 2,
        "entity_number": 205,
        "name": "fast-transport-belt",
        "position": {
          "x": 193.5,
          "y": 35.5
        }
      },
      {
        "direction": 2,
        "entity_number": 206,
        "name": "fast-transport-belt",
        "position": {
          "x": 192.5,
          "y": 35.5
        }
      },
      {
        "direction": 4,
        "entity_number": 207,
        "name": "fast-inserter",
        "position": {
          "x": 193.5,
          "y": 34.5
        }
      },
      {
        "entity_number": 208,
        "name": "medium-electric-pole",
        "neighbours": [
          201,
          174,
          217
        ],
        "position": {
          "x": 194.5,
          "y": 34.5
        }
      },
      {
        "direction": 2,
        "entity_number": 209,
        "name": "fast-transport-belt",
        "position": {
          "x": 195.5,
          "y": 35.5
        }
      },
      {
        "direction": 2,
        "entity_number": 210,
        "name": "fast-transport-belt",
        "position": {
          "x": 194.5,
          "y": 35.5
        }
      },
      {
        "direction": 2,
        "entity_number": 211,
        "name": "fast-transport-belt",
        "position": {
          "x": 197.5,
          "y": 35.5
        }
      },
      {
        "direction": 2,
        "entity_number": 212,
        "name": "fast-transport-belt",
        "position": {
          "x": 196.5,
          "y": 35.5
        }
      },
      {
        "direction": 4,
        "entity_number": 213,
        "name": "fast-inserter",
        "position": {
          "x": 196.5,
          "y": 34.5
        }
      },
      {
        "direction": 2,
        "entity_number": 214,
        "name": "fast-transport-belt",
        "position": {
          "x": 199.5,
          "y": 35.5
        }
      },
      {
        "direction": 2,
        "entity_number": 215,
        "name": "fast-transport-belt",
        "position": {
          "x": 198.5,
          "y": 35.5
        }
      },
      {
        "direction": 4,
        "entity_number": 216,
        "name": "fast-inserter",
        "position": {
          "x": 199.5,
          "y": 34.5
        }
      },
      {
        "entity_number": 217,
        "name": "medium-electric-pole",
        "neighbours": [
          208,
          220
        ],
        "position": {
          "x": 200.5,
          "y": 34.5
        }
      },
      {
        "direction": 2,
        "entity_number": 218,
        "name": "fast-transport-belt",
        "position": {
          "x": 201.5,
          "y": 35.5
        }
      },
      {
        "direction": 2,
        "entity_number": 219,
        "name": "fast-transport-belt",
        "position": {
          "x": 200.5,
          "y": 35.5
        }
      },
      {
        "entity_number": 220,
        "name": "medium-electric-pole",
        "neighbours": [
          217,
          184
        ],
        "position": {
          "x": 203.5,
          "y": 34.5
        }
      },
      {
        "direction": 2,
        "entity_number": 221,
        "name": "fast-transport-belt",
        "position": {
          "x": 203.5,
          "y": 35.5
        }
      },
      {
        "direction": 2,
        "entity_number": 222,
        "name": "fast-transport-belt",
        "position": {
          "x": 202.5,
          "y": 35.5
        }
      },
      {
        "direction": 4,
        "entity_number": 223,
        "name": "fast-inserter",
        "position": {
          "x": 202.5,
          "y": 34.5
        }
      },
      {
        "direction": 2,
        "entity_number": 224,
        "name": "fast-transport-belt",
        "position": {
          "x": 205.5,
          "y": 35.5
        }
      },
      {
        "direction": 2,
        "entity_number": 225,
        "name": "fast-transport-belt",
        "position": {
          "x": 204.5,
          "y": 35.5
        }
      },
      {
        "direction": 4,
        "entity_number": 226,
        "name": "fast-inserter",
        "position": {
          "x": 205.5,
          "y": 34.5
        }
      },
      {
        "entity_number": 227,
        "name": "fast-splitter",
        "position": {
          "x": 181,
          "y": 36.5
        }
      },
      {
        "entity_number": 228,
        "name": "fast-transport-belt",
        "position": {
          "x": 180.5,
          "y": 37.5
        }
      }
    ],
    "icons": [
      {
        "index": 1,
        "signal": {
          "name": "electronic-circuit",
          "type": "item"
        }
      }
    ],
    "item": "blueprint",
    "label": "[item=electronic-circuit] 720/m",
    "version": 281479278690304
  },
  "index": 1
}